{
"meta":{"test_sets":[],"test_metrics":[],"learn_metrics":[{"best_value":"Min","name":"RMSE"}],"launch_mode":"Train","parameters":"","iteration_count":100,"learn_sets":["learn"],"name":"experiment"},
"iterations":[
{"learn":[11.87040119],"iteration":0,"passed_time":0.05317467618,"remaining_time":5.264292941},
{"learn":[10.87854558],"iteration":1,"passed_time":0.05785871751,"remaining_time":2.835077158},
{"learn":[9.992363545],"iteration":2,"passed_time":0.06257487573,"remaining_time":2.023254315},
{"learn":[9.20903406],"iteration":3,"passed_time":0.06729148766,"remaining_time":1.614995704},
{"learn":[8.486504225],"iteration":4,"passed_time":0.07161138516,"remaining_time":1.360616318},
{"learn":[7.830078966],"iteration":5,"passed_time":0.0760560449,"remaining_time":1.191544703},
{"learn":[7.248557379],"iteration":6,"passed_time":0.08044332744,"remaining_time":1.068747065},
{"learn":[6.720602348],"iteration":7,"passed_time":0.08475738228,"remaining_time":0.9747098962},
{"learn":[6.229388401],"iteration":8,"passed_time":0.08901363554,"remaining_time":0.9000267593},
{"learn":[5.809980857],"iteration":9,"passed_time":0.09413163941,"remaining_time":0.8471847547},
{"learn":[5.4207824],"iteration":10,"passed_time":0.09841237057,"remaining_time":0.7962455437},
{"learn":[5.074023903],"iteration":11,"passed_time":0.1026249852,"remaining_time":0.7525832249},
{"learn":[4.757325738],"iteration":12,"passed_time":0.1070972201,"remaining_time":0.7167275499},
{"learn":[4.480928403],"iteration":13,"passed_time":0.1112626158,"remaining_time":0.6834703544},
{"learn":[4.236540808],"iteration":14,"passed_time":0.1154750916,"remaining_time":0.6543588523},
{"learn":[4.014570842],"iteration":15,"passed_time":0.1199188717,"remaining_time":0.6295740763},
{"learn":[3.810130007],"iteration":16,"passed_time":0.1241125501,"remaining_time":0.6059612743},
{"learn":[3.632391391],"iteration":17,"passed_time":0.1279629021,"remaining_time":0.5829421098},
{"learn":[3.472574127],"iteration":18,"passed_time":0.131912155,"remaining_time":0.5623623449},
{"learn":[3.329684968],"iteration":19,"passed_time":0.1358120739,"remaining_time":0.5432482956},
{"learn":[3.194289371],"iteration":20,"passed_time":0.1400170966,"remaining_time":0.5267309826},
{"learn":[3.07902278],"iteration":21,"passed_time":0.1442930646,"remaining_time":0.5115845018},
{"learn":[2.971275543],"iteration":22,"passed_time":0.1485285152,"remaining_time":0.4972476377},
{"learn":[2.871948833],"iteration":23,"passed_time":0.1527719565,"remaining_time":0.4837778624},
{"learn":[2.783130195],"iteration":24,"passed_time":0.1571401586,"remaining_time":0.4714204758},
{"learn":[2.701655993],"iteration":25,"passed_time":0.1611264643,"remaining_time":0.4585907062},
{"learn":[2.63177182],"iteration":26,"passed_time":0.1653669666,"remaining_time":0.4471032802},
{"learn":[2.567864298],"iteration":27,"passed_time":0.1694035198,"remaining_time":0.435609051},
{"learn":[2.51415873],"iteration":28,"passed_time":0.1732063528,"remaining_time":0.4240569327},
{"learn":[2.464336586],"iteration":29,"passed_time":0.1773969942,"remaining_time":0.4139263197},
{"learn":[2.418614328],"iteration":30,"passed_time":0.1816299833,"remaining_time":0.4042731886},
{"learn":[2.378384752],"iteration":31,"passed_time":0.1855643432,"remaining_time":0.3943242293},
{"learn":[2.342976074],"iteration":32,"passed_time":0.1896708524,"remaining_time":0.3850893065},
{"learn":[2.309198713],"iteration":33,"passed_time":0.1938830543,"remaining_time":0.376361223},
{"learn":[2.280471164],"iteration":34,"passed_time":0.1977354472,"remaining_time":0.3672229733},
{"learn":[2.25017589],"iteration":35,"passed_time":0.2016591966,"remaining_time":0.3585052384},
{"learn":[2.221050166],"iteration":36,"passed_time":0.2058242266,"remaining_time":0.3504574669},
{"learn":[2.198563144],"iteration":37,"passed_time":0.2098313343,"remaining_time":0.3423563875},
{"learn":[2.176641278],"iteration":38,"passed_time":0.2139376552,"remaining_time":0.3346204351},
{"learn":[2.155849044],"iteration":39,"passed_time":0.2181184508,"remaining_time":0.3271776763},
{"learn":[2.13719767],"iteration":40,"passed_time":0.2224145857,"remaining_time":0.3200600136},
{"learn":[2.12093172],"iteration":41,"passed_time":0.2266525903,"remaining_time":0.3129964343},
{"learn":[2.106448178],"iteration":42,"passed_time":0.230672827,"remaining_time":0.3057756079},
{"learn":[2.092517686],"iteration":43,"passed_time":0.2346347929,"remaining_time":0.2986261001},
{"learn":[2.078565759],"iteration":44,"passed_time":0.2388517749,"remaining_time":0.2919299471},
{"learn":[2.065160446],"iteration":45,"passed_time":0.2429481598,"remaining_time":0.2852000137},
{"learn":[2.052714439],"iteration":46,"passed_time":0.2470765196,"remaining_time":0.278618203},
{"learn":[2.041899881],"iteration":47,"passed_time":0.2515387918,"remaining_time":0.2725003578},
{"learn":[2.031660301],"iteration":48,"passed_time":0.2556707288,"remaining_time":0.2661062688},
{"learn":[2.021277186],"iteration":49,"passed_time":0.2596194222,"remaining_time":0.2596194222},
{"learn":[2.013030943],"iteration":50,"passed_time":0.2638274226,"remaining_time":0.2534812492},
{"learn":[2.004261869],"iteration":51,"passed_time":0.2678703347,"remaining_time":0.2472649243},
{"learn":[1.997320468],"iteration":52,"passed_time":0.2718230035,"remaining_time":0.241050588},
{"learn":[1.990200662],"iteration":53,"passed_time":0.2760081768,"remaining_time":0.2351180766},
{"learn":[1.983241894],"iteration":54,"passed_time":0.2800561206,"remaining_time":0.2291368259},
{"learn":[1.977206612],"iteration":55,"passed_time":0.2841832404,"remaining_time":0.2232868318},
{"learn":[1.971376921],"iteration":56,"passed_time":0.2885124297,"remaining_time":0.2176497277},
{"learn":[1.965627604],"iteration":57,"passed_time":0.2930422247,"remaining_time":0.2122029903},
{"learn":[1.95991373],"iteration":58,"passed_time":0.2972326901,"remaining_time":0.2065515304},
{"learn":[1.954876832],"iteration":59,"passed_time":0.3010930052,"remaining_time":0.2007286701},
{"learn":[1.950122999],"iteration":60,"passed_time":0.3051800173,"remaining_time":0.195115093},
{"learn":[1.945649871],"iteration":61,"passed_time":0.3094577145,"remaining_time":0.1896676315},
{"learn":[1.940312643],"iteration":62,"passed_time":0.3136855531,"remaining_time":0.1842280232},
{"learn":[1.935451569],"iteration":63,"passed_time":0.3176282719,"remaining_time":0.1786659029},
{"learn":[1.931312551],"iteration":64,"passed_time":0.3219548261,"remaining_time":0.173360291},
{"learn":[1.928081286],"iteration":65,"passed_time":0.3260475536,"remaining_time":0.1679638912},
{"learn":[1.924267515],"iteration":66,"passed_time":0.3302420831,"remaining_time":0.1626565484},
{"learn":[1.920514872],"iteration":67,"passed_time":0.3342545041,"remaining_time":0.1572962372},
{"learn":[1.917257913],"iteration":68,"passed_time":0.3384864052,"remaining_time":0.1520736023},
{"learn":[1.914680677],"iteration":69,"passed_time":0.3427445613,"remaining_time":0.1468905263},
{"learn":[1.911929077],"iteration":70,"passed_time":0.3467865829,"remaining_time":0.141645224},
{"learn":[1.908913037],"iteration":71,"passed_time":0.3510355915,"remaining_time":0.1365138411},
{"learn":[1.90605449],"iteration":72,"passed_time":0.3551499226,"remaining_time":0.1313568207},
{"learn":[1.903139085],"iteration":73,"passed_time":0.3593234589,"remaining_time":0.1262487828},
{"learn":[1.900421735],"iteration":74,"passed_time":0.3633343289,"remaining_time":0.121111443},
{"learn":[1.8986287],"iteration":75,"passed_time":0.3670442611,"remaining_time":0.115908714},
{"learn":[1.896131018],"iteration":76,"passed_time":0.3710665873,"remaining_time":0.1108380715},
{"learn":[1.89407454],"iteration":77,"passed_time":0.3755002523,"remaining_time":0.1059103276},
{"learn":[1.892325961],"iteration":78,"passed_time":0.3795206039,"remaining_time":0.1008852238},
{"learn":[1.890178289],"iteration":79,"passed_time":0.3835667498,"remaining_time":0.09589168746},
{"learn":[1.888209286],"iteration":80,"passed_time":0.3876074628,"remaining_time":0.09092026905},
{"learn":[1.886760523],"iteration":81,"passed_time":0.3916869602,"remaining_time":0.08598006443},
{"learn":[1.885049006],"iteration":82,"passed_time":0.3957413986,"remaining_time":0.08105546719},
{"learn":[1.883274788],"iteration":83,"passed_time":0.3999192243,"remaining_time":0.07617509034},
{"learn":[1.881585621],"iteration":84,"passed_time":0.4037577621,"remaining_time":0.07125136978},
{"learn":[1.880140653],"iteration":85,"passed_time":0.4077885151,"remaining_time":0.06638417687},
{"learn":[1.877778664],"iteration":86,"passed_time":0.4135578952,"remaining_time":0.06179600734},
{"learn":[1.875759326],"iteration":87,"passed_time":0.4183158472,"remaining_time":0.05704307007},
{"learn":[1.873905694],"iteration":88,"passed_time":0.4227811306,"remaining_time":0.0522538476},
{"learn":[1.871291466],"iteration":89,"passed_time":0.4269172389,"remaining_time":0.04743524877},
{"learn":[1.86992552],"iteration":90,"passed_time":0.431269893,"remaining_time":0.04265306634},
{"learn":[1.868541276],"iteration":91,"passed_time":0.4349794494,"remaining_time":0.03782429995},
{"learn":[1.866952883],"iteration":92,"passed_time":0.4392023219,"remaining_time":0.03305823928},
{"learn":[1.866359977],"iteration":93,"passed_time":0.4431879733,"remaining_time":0.02828859404},
{"learn":[1.865331494],"iteration":94,"passed_time":0.4479221247,"remaining_time":0.02357484867},
{"learn":[1.863699179],"iteration":95,"passed_time":0.4520868268,"remaining_time":0.01883695112},
{"learn":[1.862295823],"iteration":96,"passed_time":0.4561632578,"remaining_time":0.01410814199},
{"learn":[1.860939216],"iteration":97,"passed_time":0.4600227758,"remaining_time":0.009388219914},
{"learn":[1.859885697],"iteration":98,"passed_time":0.4640782204,"remaining_time":0.004687658792},
{"learn":[1.858477741],"iteration":99,"passed_time":0.468078027,"remaining_time":0}
]}